zenx_solver/__init__.py
zenx_solver-0.1.3.dist-info/METADATA
zenx_solver-0.1.3.dist-info/WHEEL
zenx_solver-0.1.3.dist-info/top_level.txt
zenx_solver-0.1.3.dist-info/RECORD
