Metadata-Version: 2.4
Name: zenx-solver
Version: 0.1.3
Summary: base solver
Requires-Python: >=3.13
